{
  "5029899255@qq.com" : {
    "id" : "5029899255@qq.com",
    "name" : "Jerry Stanly",
    "gender" : "M",
    "phone" : "18789378130",
    "sort" : "Muscle_Building",
    "picture" : "/img/coach/5.png",
    "time" : [ {
      "time" : "2021-06-11 10:00:00",
      "ordered" : true
    }, {
      "time" : "2021-06-12 10:00:00",
      "ordered" : true
    } ],
    "price" : 480.0,
    "description" : "Jerry, a senior fitness instructor, used to be a soldier, has excellent physical fitness. ",
    "height" : "180",
    "weight" : "70kg",
    "orders" : [ "1622537998136", "1622558492315" ]
  },
  "3029899255@qq.com" : {
    "id" : "3029899255@qq.com",
    "name" : "Tom Johnson",
    "gender" : "M",
    "phone" : "18789378130",
    "sort" : "Muscle_Building",
    "picture" : "/img/coach/3.png",
    "time" : [ {
      "time" : "2021-06-11 10:00:00",
      "ordered" : false
    }, {
      "time" : "2021-06-12 10:00:00",
      "ordered" : false
    } ],
    "price" : 550.0,
    "description" : "Tom, a national first-class sports instructor, is good at boxing and has been engaged in the fitness instruction industry for more than 20 years.",
    "height" : "180",
    "weight" : "70kg",
    "orders" : [ ]
  },
  "4029899255@qq.com" : {
    "id" : "4029899255@qq.com",
    "name" : "Marilyn Mon",
    "gender" : "F",
    "phone" : "18229389130",
    "sort" : "Lose_Weight",
    "picture" : "/img/coach/4.png",
    "time" : [ {
      "time" : "2021-06-11 10:00:00",
      "ordered" : false
    }, {
      "time" : "2021-06-12 10:00:00",
      "ordered" : true
    } ],
    "price" : 360.0,
    "description" : "She used to be a track and field athlete, is good at long-distance running.",
    "height" : "180",
    "weight" : "70kg",
    "orders" : [ "1622538133023" ]
  },
  "1029899255@qq.com" : {
    "id" : "1029899255@qq.com",
    "name" : "Kangyu Wang",
    "gender" : "M",
    "phone" : "15510412588",
    "sort" : "Lose_Weight",
    "picture" : "/img/coach/1.png",
    "time" : [ {
      "time" : "2021-06-11 10:00:00",
      "ordered" : false
    }, {
      "time" : "2021-06-12 10:00:00",
      "ordered" : false
    } ],
    "price" : 200.0,
    "description" : "He served in small military operations before retiring as a fitness instructor and has been in the business for 12 years now. ",
    "height" : "180",
    "weight" : "70kg",
    "orders" : [ ]
  },
  "2029899255@qq.com" : {
    "id" : "2029899255@qq.com",
    "name" : "Jennifer Jessica",
    "gender" : "F",
    "phone" : "18789378130",
    "sort" : "Warm_Up",
    "picture" : "/img/coach/2.png",
    "time" : [ {
      "time" : "2021-06-11 10:00:00",
      "ordered" : true
    }, {
      "time" : "2021-06-12 10:00:00",
      "ordered" : false
    } ],
    "price" : 260.0,
    "description" : "A young female fitness instructor, graduated from a prestigious university. She loves bodybuilding and teaches patiently. She is often praised by her students.",
    "height" : "170cm",
    "weight" : "60kg",
    "orders" : [ "1622538028371" ]
  }
}